Workbook

Sheet BP
B2: Informar o ANO de PREENCHIMENTO | E2: 2025
C6: ATIVO | D6: Link | E6: =$E$2 -> 2025 | F6: AV% | H6: PASSIVO | I6: Link | J6: =$E$2 -> 2025 | K6: AV%
C8: CIRCULANTE | E8: =SUM(E9:E13) -> 1012000 | F8: =IF($E$28=0,0,E8/$E$28) -> 0.56949916 | H8: CIRCULANTE | J8: =SUM(J9:J13) -> 686200 | K8: =IF($J$28=0,0,J8/$J$28) -> 0.38615644
C9: Caixa e Equivalentes de Caixa | D9: A.01 | E9: =A.01!$G$29 -> 330000 | F9: =IF($E$28=0,0,E9/$E$28) -> 0.18570625 | H9: Contas a Pagar | I9: P.01 | J9: =P.01!$G$32 -> 400000 | K9: =IF($J$28=0,0,J9/$J$28) -> 0.22509848
C10: Contas a Receber | D10: A.02 | E10: =A.02!$G$33 -> 205000 | F10: =IF($E$28=0,0,E10/$E$28) -> 0.11536297 | H10: Empréstimos e Financiamentos | I10: P.02 | J10: =P.02!$G$9 -> 95000 | K10: =IF($J$28=0,0,J10/$J$28) -> 0.053460889
C11: Adiantamentos | D11: A.03 | E11: =A.03!$G$15 -> 50000 | F11: =IF($E$28=0,0,E11/$E$28) -> 0.02813731 | H11: Obrigações Trabalhistas | I11: P.03 | J11: =P.03!$G$18 -> 155000 | K11: =IF($J$28=0,0,J11/$J$28) -> 0.087225661
C12: Estoques | D12: A.04 | E12: =A.04!$G$17 -> 425000 | F12: =IF($E$28=0,0,E12/$E$28) -> 0.23916714 | H12: Obrigações Tributárias | I12: P.04 | J12: =P.04!$G$21 -> 35000 | K12: =IF($J$28=0,0,J12/$J$28) -> 0.019696117
C13: Outros Créditos de Curto Prazo | D13: A.05 | E13: =A.05!$G$9 -> 2000 | F13: =IF($E$28=0,0,E13/$E$28) -> 0.0011254924 | H13: Outros Débitos de Curto Prazo | I13: P.05 | J13: =P.05!$G$9 -> 1200 | K13: =IF($J$28=0,0,J13/$J$28) -> 0.00067529544
C15: NÃO CIRCULANTE | E15: =E16+E19 -> 765000 | F15: =IF($E$28=0,0,E15/$E$28) -> 0.43050084 | H15: NÃO CIRCULANTE | J15: =J16 -> 420000 | K15: =IF($J$28=0,0,J15/$J$28) -> 0.2363534
C16: Realizável a Longo Prazo | E16: =SUM(E17:E18) -> 0 | F16: =IF($E$28=0,0,E16/$E$28) -> 0 | H16: Exigível a Longo Prazo | J16: =SUM(J17:J20) -> 420000 | K16: =IF($J$28=0,0,J16/$J$28) -> 0.2363534
C17: Contas a Receber | D17: A.02 | E17: =A.02!$G$34 -> 0 | F17: =IF($E$28=0,0,E17/$E$28) -> 0 | H17: Contas a Pagar | I17: P.01 | J17: =P.01!$G$33 -> 380000 | K17: =IF($J$28=0,0,J17/$J$28) -> 0.21384356
C18: Outros Créditos de Longo Prazo | D18: A.05 | E18: =A.05!$G$15 -> 0 | F18: =IF($E$28=0,0,E18/$E$28) -> 0 | H18: Emprestimos e Financiamentos | I18: P.02 | J18: =P.02!$G$17 -> 40000 | K18: =IF($J$28=0,0,J18/$J$28) -> 0.022509848
C19: Ativo Permanente | E19: =SUM(E20:E22) -> 765000 | F19: =IF($E$28=0,0,E19/$E$28) -> 0.43050084 | H19: Obrigações Tributárias | I19: P.04 | J19: =P.04!$G$22 -> 0 | K19: =IF($J$28=0,0,J19/$J$28) -> 0
C20: Investimentos | D20: A.06 | E20: =A.06!$G$15 -> 200000 | F20: =IF($E$28=0,0,E20/$E$28) -> 0.11254924 | H20: Outros Débitos de Longo Prazo | I20: P.05 | J20: =P.05!$G$17 -> 0 | K20: =IF($J$28=0,0,J20/$J$28) -> 0
C21: Imobilizado | D21: A.07 | E21: =A.07!$J$30 -> 565000 | F21: =IF($E$28=0,0,E21/$E$28) -> 0.3179516
H22: PATRIMÔNIO LÍQUIDO | J22: =SUM(J23:J26) -> 670800 | K22: =IF($J$28=0,0,J22/$J$28) -> 0.37749015
H23: Capital Social | I23: P.06 | J23: =P.06!$G$9 -> 500000 | K23: =IF($J$28=0,0,J23/$J$28) -> 0.2813731
H24: (-) Capital social a Integralizar | I24: P.06 | J24: =-P.06!$G$11 -> 0 | K24: =IF($J$28=0,0,J24/$J$28) -> 0
H25: Sobras/Perdas do Exercício | I25: DSP | J25: =DSP!$E$33 -> 52000 | K25: =IF($J$28=0,0,J25/$J$28) -> 0.029262802
H26: Sobras/Perdas Acumuladas | J26: =$E$28-$J$8-$J$15-($J$23+$J$24+$J$25) -> 118800 | K26: =IF($J$28=0,0,J26/$J$28) -> 0.066854249
C28: TOTAL DO ATIVO | E28: =E8+E15 -> 1777000 | F28: =IF($E$28=0,0,E28/$E$28) -> 1 | H28: TOTAL DO PASSIVO + PL | J28: =J8+J15+J22 -> 1777000 | K28: =IF($J$28=0,0,J28/$J$28) -> 1

Sheet DSP
C3: DEMONSTRATIVO DE SOBRAS E PERDAS | D3: Link | E3: =BP!$E$2 -> 2025 | F3: AV%
C5: INGRESSOS/RECEITA DE VENDAS | D5: C.01 | E5: ='C.01'!G9 -> 53500 | F5: =IF($E$5=0,0,E5/$E$5) -> 1
C7: (-) Devoluções de Vendas | D7: C.02 | E7: =-'C.02'!$G$9 -> 0 | F7: =IF($E$5=0,0,E7/$E$5) -> 0
C8: (-) Impostos sobre Vendas | D8: C.02 | E8: =-'C.02'!$G$13 -> -1500 | F8: =IF($E$5=0,0,E8/$E$5) -> -0.028037383
C10: INGRESSOS/RECEITA LÍQUIDA | E10: =E5+E7+E8 -> 52000 | F10: =IF($E$5=0,0,E10/$E$5) -> 0.97196262
C12: (-) DISPÊNDIO/CUSTOS DE VENDAS | D12: C.03 | E12: ='C.03'!$I$14 -> 0 | F12: =IF($E$5=0,0,E12/$E$5) -> 0
C14: RESULTADO BRUTO | E14: =E10+E12 -> 52000 | F14: =IF($E$5=0,0,E14/$E$5) -> 0.97196262
C16: (-) DISPÊNDIOS e DESPESAS OPERACIONAIS | E16: =SUM(E17:E22) -> 0 | F16: =IF($E$5=0,0,E16/$E$5) -> 0
C17: (-) Despesas Comerciais | D17: C.04 | E17: =-'C.04'!$G$19 -> 0 | F17: =IF($E$5=0,0,E17/$E$5) -> 0
C18: (-) Despesas com Pessoal | D18: C.05 | E18: =-'C.05'!$G$20 -> 0 | F18: =IF($E$5=0,0,E18/$E$5) -> 0
C19: (-) Despesas Administrativas | D19: C.06 | E19: =-'C.06'!$G$20 -> 0 | F19: =IF($E$5=0,0,E19/$E$5) -> 0
C20: (-) Despesas Tributárias | D20: C.07 | E20: =-'C.07'!G14 -> 0 | F20: =IF($E$5=0,0,E20/$E$5) -> 0
C21: (+) Outros Ingressos/Receitas Operacionais | D21: C.08 | E21: ='C.08'!$G$13 -> 0 | F21: =IF($E$5=0,0,E21/$E$5) -> 0
C22: (-) Outros Dispêndios/Despesas Operacionais | D22: C.08 | E22: =-'C.08'!$G$19 -> 0 | F22: =IF($E$5=0,0,E22/$E$5) -> 0
C24: EBITDA | E24: =E14+E16 -> 52000 | F24: =IF($E$5=0,0,E24/$E$5) -> 0.97196262
C26: (-) Depreciação | D26: A.07 | E26: =A.07!$I$20 -> 0 | F26: =IF($E$5=0,0,E26/$E$5) -> 0
C27: (+) Ingressos/Receitas Financeiras | D27: C.09 | E27: ='C.09'!$G$14 -> 0 | F27: =IF($E$5=0,0,E27/$E$5) -> 0
C28: (-) Dispêndios/Despesas Financeiras | D28: C.09 | E28: =-'C.09'!$G$22 -> 0 | F28: =IF($E$5=0,0,E28/$E$5) -> 0
C30: RESULTADO ANTES IR/CSLL | E30: =SUM(E24:E28) -> 52000 | F30: =IF($E$5=0,0,E30/$E$5) -> 0.97196262
C31: (-) Provisão p/ IRPJ/CSLL | D31: C.10 | E31: =-'C.10'!$G$13 -> 0 | F31: =IF($E$5=0,0,E31/$E$5) -> 0
C33: SOBRA/PERDAS DO EXERCÍCIO | E33: =E30+E31 -> 52000 | F33: =IF($E$5=0,0,E33/$E$5) -> 0.97196262

Sheet INDICADORES
C3: INDICADORES FINANCEIROS
C6: EFICIÊNCIA ECONÔMICA E FINANCEIRA | F6: ENDIVIDAMENTO
D8: =BP!$E$2 -> 2025 | G8: =BP!$E$2 -> 2025
C9: Liquidez Geral (Total) | D9: =IFERROR((BP!$E$8+BP!$E$16)/(BP!$J$8+BP!$J$15),0) -> 0.91484361 | F9: Nível de Alavancagem (EBITDA) | G9: =IFERROR((BP!$J$10+BP!$J$18-BP!$E$9)/DSP!$E$24,0) -> -3.75
C10: Liquidez Corrente | D10: =IFERROR((BP!$E$8)/(BP!$J$8),0) -> 1.4747887 | F10: Endividamento Operacional (%) | G10: =IFERROR(((BP!$J$8-BP!$J$10)+(BP!$J$15-BP!$J$18))/BP!$E$28,0) -> 0.54653911
C11: Liquidez Seca | D11: =IFERROR((BP!$E$8-BP!$E$12)/(BP!$J$8),0) -> 0.85543573 | F11: Endividamento Financeiro Total (%) | G11: =IFERROR((BP!$J$10+BP!$J$18)/BP!$E$28,0) -> 0.075970737
C12: Garantia ao Capital de Terceiros | D12: =IFERROR((BP!$E$28)/(BP!$J$8+BP!$J$15),0) -> 1.6064003 | F12: Endividamento Financeiro LP (%) | G12: =IFERROR(BP!$J$18/BP!$E$28,0) -> 0.022509848
C13: Imobilização dos Recursos Próprios | D13: =IFERROR(BP!$E$19/BP!$J$22,0) -> 1.1404293 | F13: Endividamento de Longo Prazo (%) | G13: =IFERROR(BP!$J$15/BP!$E$28,0) -> 0.2363534
C14: Imobilização dos Recursos Próprios (%) | D14: =IFERROR(BP!$E$19/BP!$J$22,0) -> 1.1404293 | F14: Endividamento Total (%) | G14: =IFERROR((BP!$J$8+BP!$J$15)/BP!$E$28,0) -> 0.62250985
C15: EBITDA | D15: =DSP!$E$24 -> 52000 | F15: Perfil do Endividamento (%) | G15: =IFERROR(BP!$J$8/(BP!$J$8+BP!$J$15),0) -> 0.62032182
C16: Inadimplência Total sobre Créditos (%) | D16: =IFERROR(-(A.02!$G$31/A.02!$G$29),0) -> 0
C19: RENTABILIDADE | F19: CAPACIDADE OPERACIONAL
D21: =BP!$E$2 -> 2025 | G21: =BP!$E$2 -> 2025
C22: Rentabilidade do Capital Integralizado (%) | D22: =IFERROR(DSP!$E$33/(BP!$J$23+BP!$J$24),0) -> 0.104 | F22: Prazo Médio de Estoque - PME | G22: =IFERROR(BP!$E$12/-DSP!$E$12*360,0) -> 0
C23: Rentabilidade dos Ingressos (%) | D23: =IFERROR(DSP!$E$33/DSP!$E$10,0) -> 1 | F23: Prazo Médio de Recebimento - PMR | G23: =IFERROR((BP!$E$10+BP!$E$13)/DSP!$E$10*360,0) -> 1433.0769
C24: Rentabilidade do Patrimônio Líquido (%) | D24: =IFERROR(DSP!$E$33/BP!$J$22,0) -> 0.07751938 | F24: Prazo Médio de Pagamento - PMP | G24: =IFERROR((BP!$J$8-BP!$J$10)/(DSP!$E$12+DSP!E16+DSP!$E$26)*360,0) -> 0
C25: Rentabilidade dos Ativos (%) | D25: =IFERROR(DSP!$E$33/BP!$E$28,0) -> 0.029262802 | F25: Ciclo Operacional | G25: =G22+G23 -> 1433.0769
F26: Ciclo Financeiro | G26: =G25-G24 -> 1433.0769
F27: Giro do Ativo | G27: =IFERROR(DSP!$E$10/BP!$E$28,0) -> 0.029262802
C28: TESOURARIA | F28: Giro do Permanente | G28: =IFERROR(DSP!$E$10/BP!$E$19,0) -> 0.067973856
D30: =D8 -> 2025
C31: Capital de Giro (R$) | D31: =IFERROR((BP!$E$8-BP!$J$8),0) -> 325800
C32: Capital de Giro - Faturamento (%) | D32: =IFERROR((BP!$E$8-BP!$J$8)/DSP!$E$10,0) -> 6.2653846
C33: Capital de Giro (%) | D33: =IFERROR((BP!$E$8-BP!$J$8)/BP!$E$28,0) -> 0.18334271
C34: Capital de Giro Próprio (%) | D34: =IFERROR((BP!$J$22-BP!$E$15)/BP!$E$28,0) -> -0.053010692
C35: Necessidade de Capital de Giro (R$) | D35: =IFERROR((BP!$E$8-BP!$E$9)-(BP!$J$8-BP!$J$10),0) -> 90800
C36: Necessidade de Capital de Giro - Faturamento (%) | D36: =IFERROR($D$35/DSP!$E$10,0) -> 1.7461538
C37: Necessidade de Capital de Giro (%) | D37: =IFERROR($D$35/BP!$E$28,0) -> 0.051097355
C38: Tesouraria (R$) | D38: =IFERROR((BP!$E$9-BP!$J$10),0) -> 235000
C39: Tesouraria - Faturamento (%) | D39: =IFERROR($D$38/DSP!$E$10,0) -> 4.5192308
C40: Tesouraria (%) | D40: =IFERROR($D$38/BP!$E$28,0) -> 0.13224536
C41: Independência Financeira | D41: =IFERROR(BP!$J$22/BP!$E$28,0) -> 0.37749015
C42: Índice de Auto-Financiamento | D42: =IFERROR($D$31/$D$35,0) -> 3.5881057

Sheet A.01
B2: << Voltar
D5: A.01 | E5: Caixa e Equivalente Caixa
E6: (Valores em R$, saldo no último dia do ano)
G7: =BP!$E$2 -> 2025 | I7: Pergunta
E9: Saldo em Caixa | G9: =SUM($G$11:$G$11) -> 100000 | I9: Qual o valor que a Cooperativa possuía em espécie no caixa?
E11: Caixa Geral | G11: 100000
E13: Saldo em Conta Corrente | G13: =SUM(G15:G19) -> 80000 | I13: Qual o saldo em contas correntes bancárias da Cooperativa, desconsiderando-se as aplicações?
E15: Banco A | G15: 50000
E16: Banco B | G16: 30000
E17: Banco C | G17: 0
E18: Banco D | G18: 0
E19: Demais Bancos | G19: 0
E21: Saldo em Aplicações Financeiras | G21: =SUM(G23:G27) -> 150000 | I21: Qual o saldo em aplicações financeiras da Cooperativa?
E23: Banco A | G23: 150000
E24: Banco B | G24: 0
E25: Banco C | G25: 0
E26: Banco D | G26: 0
E27: Demais Bancos | G27: 0
E29: Caixa e Equivalente Caixa | G29: =G9+G13+G21 -> 330000

Sheet A.02
B2: << Voltar
D5: A.02 | E5: Contas a Receber
E6: (Valores em R$, saldo no último dia do ano)
G7: =BP!$E$2 -> 2025 | I7: Pergunta
E9: Cooperados | G9: =SUM(G11:G17) -> 205000 | I9: Qual o valor de títulos (duplicatas, boletos, cheques) a receber da Cooperativa, com atos cooperados, vencidos ou a vencer?
E11: Títulos e Duplicatas a Vencer em até 12 meses | G11: 205000
E12: Títulos e Duplicatas a Vencer após 12 meses | G12: 0
E13: Títulos e Duplicatas Vencidos até 30 dias | G13: 0
E14: Títulos e Duplicatas Vencidos de 31 até 60 dias | G14: 0
E15: Títulos e Duplicatas Vencidos de 61 até 90 dias | G15: 0
E16: Títulos e Duplicatas Vencidos de 91 até 180 dias | G16: 0
E17: Títulos e Duplicatas Vencidos há mais de 180 dias | G17: 0
E19: Não Cooperados | G19: =SUM(G21:G27) -> 0 | I19: Qual o valor de títulos (duplicatas, boletos, cheques) a receber da Cooperativa, com atos não cooperados, vencidos ou a vencer?
E21: Títulos e Duplicatas a Vencer em até 12 meses | G21: 0
E22: Títulos e Duplicatas a Vencer após 12 meses | G22: 0
E23: Títulos e Duplicatas Vencidos até 30 dias | G23: 0
E24: Títulos e Duplicatas Vencidos de 31 até 60 dias | G24: 0
E25: Títulos e Duplicatas Vencidos de 61 até 90 dias | G25: 0
E26: Títulos e Duplicatas Vencidos de 91 até 180 dias | G26: 0
E27: Títulos e Duplicatas Vencidos há mais de 180 dias | G27: 0
E29: Total Cooperados e Não Cooperados | G29: =G9+G19 -> 205000
I30: Qual o valor das perda estimada de curto e longo prazo da cooperativa?
E31: Perdas estimadas do contas a receber | F31: =IFERROR(G31/G29,0) -> 0 | G31: 0
E33: Contas a Receber no Curto Prazo | G33: =G29-G34 -> 205000
E34: Contas a Receber no Longo Prazo | G34: =G12+G22 -> 0

Sheet A.03
B2: << Voltar
D5: A.03 | E5: Adiantamentos
E6: (Valores em R$, saldo no último dia do ano)
G7: =BP!$E$2 -> 2025 | I7: Pergunta
E9: Adiantamentos a Funcionários | G9: 0 | I9: A Cooperativa fez algum pagamento antecipado para funcionários, fornecedores, compras diversas até a data, mas que o serviço não tenha sido prestado, ou o produto não tenha sido entregue?
E10: Adiantamentos a Fornecedores - Cooperados | G10: 50000
E11: Adiantamentos a Fornecedores - Não Cooperados | G11: 0
E12: Adiantamentos a Dirigentes | G12: 0
E13: Adiantamentos Diversos | G13: 0
E15: Total Adiantamentos | G15: =SUM(G9:G13) -> 50000

Sheet A.04
B2: << Voltar
D5: A.04 | E5: Estoques
E6: (Valores em R$, saldo no último dia do ano)
G7: =BP!$E$2 -> 2025 | I7: Pergunta
E9: Matérias-Primas | G9: 20000 | I9: Qual o valor do estoque da Cooperativa, para cada um dos grupos listados?
E10: Produtos em Elaboração | G10: 5000
E11: Produtos Acabados | G11: 150000
E12: Marcadorias para Revenda | G12: 250000
E13: Materiais Diversos | G13: 0
E14: Estoque da Cooperativa em Poder de Terceiros | G14: 0
E15: Estoque de Terceiros em Poder da Cooperativa | G15: 0
E17: Total Estoque | G17: =SUM(G9:G15) -> 425000

Sheet A.05
B2: << Voltar
D5: A.05 | E5: Outros Créditos
E6: (Valores em R$, saldo no último dia do ano)
G7: =BP!$E$2 -> 2025 | I7: Pergunta
E9: Curto Prazo | G9: =SUM(G11:G13) -> 2000
E11: Impostos a Recuperar | G11: 0 | I11: A Cooperativa possui outros valores a receber, ou direitos contra terceiros com previsão de recebimento para os próximos 12 meses?
E12: Depósitos Judiciais | G12: 2000
E13: Demais Créditos | G13: 0
E15: Longo Prazo | G15: =SUM(G17:G19) -> 0
E17: Impostos a Recuperar | G17: 0 | I17: A Cooperativa possui outros valores a receber, ou direitos contra terceiros com previsão de recebimento após os próximos 12 meses?
E18: Depósitos Judiciais | G18: 0
E19: Demais Créditos | G19: 0
E21: Total Outros Créditos | G21: =$G$9+$G$15 -> 2000

Sheet A.06
B2: << Voltar
D5: A.06 | E5: Investimentos
E6: (Valores em R$, saldo no último dia do ano)
G7: =BP!$E$2 -> 2025 | I7: Pergunta
E9: Participações Societárias em Outras Empresas | G9: 0 | I9: Qual o valor para os investimentos realizados pela Cooperativa?
E10: Imóveis para Renda [ Aluguel ] | G10: 200000
E11: Imóveis para Investimento | G11: 0
E12: Quadros e Obras de Arte | G12: 0
E13: Demais Investimentos | G13: 0
E15: Total Investimentos | G15: =SUM(G9:G13) -> 200000

Sheet A.07
B2: << Voltar
D5: A.07 | E5: Imobilizado Líquido
E6: (Valores em R$, saldo no último dia do ano)
J7: =BP!$E$2 -> 2025 | L7: Pergunta
E9: Imobilizado Bruto | J9: =SUM(J11:J17) -> 565000
E11: Imóveis e Instalações | J11: 100000 | L11: Qual o valor para os Ativos Imobilizados listados, considerando o valor pago na data de aquisição?
E12: Máquinas e Equipamentos | J12: 100000
E13: Móveis e Utensílios | J13: 50000
E14: Equipamentos de Informática | J14: 300000
E15: Veículos | J15: 15000
E16: Máquinas e Implementos Agrícolas | J16: 0
E17: Demais itens do Ativo Imobilizado | J17: 0
E20: Depreciação Acumulada | G20: Média (ano) | H20: Taxa (aa) | I20: =SUM(I22:I28) -> 0 | J20: =SUM(J22:J28) -> 0
E22: Imóveis e Instalações | G22: 0 | H22: =IF(G22=0,0,(1/G22)) -> 0 | I22: =-J11*H22 -> 0 | J22: =G22*I22 -> 0 | L22: OBS. A depreciação acumulada será calculada automaticamente, considerando a taxa padrão de depreciação dos bens do ativo imobilizado, multiplicado pela média da vida útil dos bens. Caso a Cooperativa mantenha controle patrimonial dos bens, poderá informar o valor da depreciação acumulada em seus controles.
E23: Máquinas e Equipamentos | G23: 0 | H23: =IF(G23=0,0,(1/G23)) -> 0 | I23: =-J12*H23 -> 0 | J23: =G23*I23 -> 0
E24: Móveis e Utensílios | G24: 0 | H24: =IF(G24=0,0,(1/G24)) -> 0 | I24: =-J13*H24 -> 0 | J24: =G24*I24 -> 0
E25: Equipamentos de Informática | G25: 0 | H25: =IF(G25=0,0,(1/G25)) -> 0 | I25: =-J14*H25 -> 0 | J25: =G25*I25 -> 0
E26: Veículos | G26: 0 | H26: =IF(G26=0,0,(1/G26)) -> 0 | I26: =-J15*H26 -> 0 | J26: =G26*I26 -> 0
E27: Máquinas e Implementos Agrícolas | G27: 0 | H27: =IF(G27=0,0,(1/G27)) -> 0 | I27: =-J16*H27 -> 0 | J27: =G27*I27 -> 0
E28: Demais itens do Ativo Imobilizado | G28: 0 | H28: =IF(G28=0,0,(1/G28)) -> 0 | I28: =-J17*H28 -> 0 | J28: =G28*I28 -> 0
E30: Imobilizado Líquido | J30: =J9+J20 -> 565000

Sheet P.01
B2: << Voltar
D5: P.01 | E5: Contas a Pagar
E6: (Valores em R$, saldo no último dia do ano)
G7: =BP!$E$2 -> 2025 | I7: Pergunta
E9: Cooperados | G9: =SUM(G11:G17) -> 180000 | I9: Qual o valor de títulos, duplicatas, boletos, cheques a pagar para cooperados, vencidos ou a vencer?
E11: Títulos e Duplicatas a Vencer em até 12 meses | G11: 150000
E12: Títulos e Duplicatas a Vencer após 12 meses | G12: 30000
E13: Títulos e Duplicatas Vencidos até 30 dias | G13: 0
E14: Títulos e Duplicatas Vencidos de 31 até 60 dias | G14: 0
E15: Títulos e Duplicatas Vencidos de 61 até 90 dias | G15: 0
E16: Títulos e Duplicatas Vencidos de 91 até 180 dias | G16: 0
E17: Títulos e Duplicatas Vencidos há mais de 180 dias | G17: 0
E19: Não Cooperados | G19: =SUM(G21:G27) -> 600000 | I19: Qual o valor de títulos, duplicatas, boletos, cheques a pagar para não cooperados, vencidos ou a vencer?
E21: Títulos e Duplicatas a Vencer em até 12 meses | G21: 250000
E22: Títulos e Duplicatas a Vencer após 12 meses | G22: 350000
E23: Títulos e Duplicatas Vencidos até 30 dias | G23: 0
E24: Títulos e Duplicatas Vencidos de 31 até 60 dias | G24: 0
E25: Títulos e Duplicatas Vencidos de 61 até 90 dias | G25: 0
E26: Títulos e Duplicatas Vencidos de 91 até 180 dias | G26: 0
E27: Títulos e Duplicatas Vencidos há mais de 180 dias | G27: 0
E29: Total Cooperados e Não Cooperados | G29: =G9+G19 -> 780000
E32: Contas a Pagar no Curto Prazo | G32: =G29-G33 -> 400000
E33: Contas a Pagar no Longo Prazo | G33: =G12+G22 -> 380000

Sheet P.02
B2: << Voltar
D5: P.02 | E5: Empréstimos e Financiamentos
E6: (Valores em R$, saldo no último dia do ano)
G7: =BP!$E$2 -> 2025 | I7: Pergunta
E9: Curto Prazo | G9: =SUM(G11:G15) -> 95000 | I9: Qual o valor das parcelas de empréstimos e financiamentos a vencer nos próximos 12 meses?
E11: Banco A | G11: 60000
E12: Banco B | G12: 35000
E13: Banco C | G13: 0
E14: Banco D | G14: 0
E15: Demais Bancos | G15: 0
E17: Longo Prazo | G17: =SUM(G19:G23) -> 40000 | I17: Qual o valor das parcelas de empréstimos e financiamentos a vencer após os próximos 12 meses?
E19: Banco A | G19: 15000
E20: Banco B | G20: 25000
E21: Banco C | G21: 0
E22: Banco D | G22: 0
E23: Demais Bancos | G23: 0
E25: Total dos Empréstimos e Financiamentos | G25: =G9+G17 -> 135000

Sheet P.03
B2: << Voltar
D5: P.03 | E5: Obrigações Trabalhistas
E6: (Valores em R$, saldo no último dia do ano)
G7: =BP!$E$2 -> 2025 | I7: Pergunta
I8: Qual o valor de salários e encargos trabalhistas a pagar pela Cooperativa, no último dia do ano?
E9: Salários a pagar | G9: 55000
E10: Férias a pagar | G10: 20000
E11: Decimo terceiro a pagar | G11: 23000
E12: Rescisões a pagar | G12: 0
E13: INSS a pagar | G13: 35000
E14: FGTS a pagar | G14: 0
E15: Multa FGTS a pagar | G15: 0
E16: IRRF sobre folha a pagar | G16: 22000
G18: =SUM(G9:G16) -> 155000

Sheet P.04
B2: << Voltar
D5: P.04 | E5: Obrigações Tributárias
E6: (Valores em R$, saldo no último dia do ano)
G7: =BP!$E$2 -> 2025 | I7: Pergunta
I8: Qual o valor dos tributos (impostos e taxas) a pagar devidos pela Cooperativa, no último dia do ano? Devem constar também os parcelamentos realizados pela Cooperativa?
E9: ISS a recolher | G9: 0
E10: ICMS a recolher | G10: 20000
E11: PIS a recolher | G11: 0
E12: COFINS a recolher | G12: 0
E13: IRPJ a recolher | G13: 15000
E14: CSLL a recolher | G14: 0
E15: Demais impostos e taxas (IPTU, IPVA etc.) | G15: 0
E16: Parcelamentos tributários (próximos 12 meses) | G16: 0
E17: Parcelamentos tributários (após 12 meses) | G17: 0
G19: =SUM(G9:G17) -> 35000
E21: Obrigações Tributárias de Curto Prazo | G21: =G19-G22 -> 35000
E22: Obrigações Tributárias de Longo Prazo | G22: =G17 -> 0

Sheet P.05
B2: << Voltar
D5: P.05 | E5: Outros Débitos
E6: (Valores em R$, saldo no último dia do ano)
G7: =BP!$E$2 -> 2025 | I7: Pergunta
E9: Curto Prazo | G9: =SUM(G11:G13) -> 1200 | I9: A Cooperativa possui outros valores a pagar, ou obrigações contra terceiros com previsão de pagamento para os próximos 12 meses?
E11: Adiantamento de clientes | G11: 1200
E12: Vendas para entrega futura | G12: 0
E13: Demais debitos e obrigações | G13: 0
E17: Longo Prazo | G17: =SUM(G19:G21) -> 0 | I17: A Cooperativa possui outros valores a pagar, ou obrigações contra terceiros com previsão de pagamento após os próximos 12 meses?
E19: Adiantamento de clientes | G19: 0
E20: Vendas para entrega futura | G20: 0
E21: Demais debitos e obrigações | G21: 0
E23: Total Longo Prazo | G23: =$G$9+$G$17 -> 1200

Sheet P.06
B2: << Voltar
D5: P.06 | E5: Capital Social
E6: (Valores em R$, saldo no último dia do ano)
G7: =BP!$E$2 -> 2025 | I7: Pergunta
E9: Capital Social | G9: 500000 | I9: Qual o valor do capital social da cooperativa? Caso haja capital social a integralizar, favor informar.
E11: Capital Social a Integralizar | G11: 0
E13: Total Capital Social | G13: =G9-G11 -> 500000

Sheet C.01
B2: << Voltar
D5: C.01 | E5: Ingressos e Receita de Vendas
E6: (Valores em R$, total do ano)
G7: =BP!$E$2 -> 2025 | I7: Pergunta
G9: =SUM(G11:G14) -> 53500 | I9: Qual o valor das vendas de produtos e serviços para cooperados e não cooperados no exercício corrente?
E11: Venda de produtos para Cooperados | G11: 15000
E12: Venda de produtos para Não Cooperados | G12: 2000
E13: Venda de serviços para Cooperados | G13: 35000
E14: Venda de serviços para Não Cooperados | G14: 1500

Sheet C.02
B2: << Voltar
D5: C.02 | E5: Devoluções e Impostos sobre Vendas
E6: (Valores em R$, total do ano)
G7: =BP!$E$2 -> 2025 | I7: Pergunta
G9: =G11 -> 0
E11: Devolução de Vendas | G11: 0 | I11: Qual o valor das devoluções de venda do período?
G13: =SUM(G15:G19) -> 1500
E15: ICMS | G15: 1500 | I15: Qual o valor dos impostos sobre venda do período?
E16: PIS | G16: 0
E17: COFINS | G17: 0
E18: ISS | G18: 0
E20: Total Devoluções e Impostos sobre Vendas | G20: =$G$9+$G$13 -> 1500

Sheet C.03
B2: << Voltar
D5: C.03 | E5: Dispêndio/Custos de Vendas
E6: (Valores em R$, total do ano)
I7: =BP!$E$2 -> 2025 | K7: Pergunta
G8: Margem Bruta
E9: Custo de produtos para Cooperados | G9: 0 | I9: =IF(G9=0,0,-'C.01'!G11*(1-'C.03'!G9)) -> 0 | K9: Informar a margem bruta (MÉDIA) estimada para produtos e servicos da cooperativa. Para definir a margem bruta, considere o valor da venda os custos médios de compra de produtos e de prestação de serviços.
E10: Custo de produtos para Não Cooperados | G10: 0 | I10: =IF(G10=0,0,-'C.01'!G12*(1-'C.03'!G10)) -> 0
E11: Custo de serviços para Cooperados | G11: 0 | I11: =IF(G11=0,0,-'C.01'!G13*(1-'C.03'!G11)) -> 0
E12: Custo de serviços para Não Cooperados | G12: 0 | I12: =IF(G12=0,0,-'C.01'!G14*(1-'C.03'!G12)) -> 0
E14: Total Dispêndio/Custos de Vendas | I14: =SUM(I9:I13) -> 0

Sheet C.04
B2: << Voltar
D5: C.04 | E5: Despesas Comerciais
E6: (Valores em R$, total do ano)
G7: =BP!$E$2 -> 2025 | I7: Pergunta
E9: Comissão de vendas | G9: 0 | I9: Qual o valor das despesas comerciais do período?
E10: Publicidade e Propaganda | G10: 0
E11: Feiras e Eventos | G11: 0
E12: Brindes | G12: 0
E13: Midias Sociais | G13: 0
E14: Fretes de vendas | G14: 0
E15: Bonificações | G15: 0
E16: Despesas de viagem | G16: 0
E17: Outras despesas comerciais | G17: 0
E19: Total das Despesas Comerciais | G19: =SUM(G9:G17) -> 0

Sheet C.05
B2: << Voltar
D5: C.05 | E5: Despesas com Pessoal
E6: (Valores em R$, total do ano)
G7: =BP!$E$2 -> 2025 | I7: Pergunta
E9: Salários e Ordenados | G9: 0 | I9: Qual o valor das despesas com pessoal do período?
E10: INSS | G10: 0
E11: Fgts | G11: 0
E12: Rescisão | G12: 0
E13: Férias | G13: 0
E14: Décimo Terceiro | G14: 0
E15: Vale Alimentação | G15: 0
E16: Vale Transporte | G16: 0
E17: Plano de Saúde | G17: 0
E18: Demais Benefícios | G18: 0
E20: Total Despesas com Pessoal | G20: =SUM(G9:G18) -> 0

Sheet C.06
B2: << Voltar
D5: C.06 | E5: Despesas Administrativas
E6: (Valores em R$, total do ano)
G7: =BP!$E$2 -> 2025 | I7: Pergunta
E9: Aluguel | G9: 0 | I9: Qual o valor das despesas administrativas do período?
E10: Água e Esgoto | G10: 0
E11: Energia Elétrica | G11: 0
E12: Telefonia e Internet | G12: 0
E13: Seguros | G13: 0
E14: Serviços de terceiros PJ | G14: 0
E15: Manutenção em geral | G15: 0
E16: Material de consumo | G16: 0
E17: Bens de pequeno valor | G17: 0
E18: Outras despesas administrativas | G18: 0
E20: Total Despesas Administrativas | G20: =SUM(G9:G18) -> 0

Sheet C.07
B2: << Voltar
D5: C.07 | E5: Despesas Tributárias
E6: (Valores em R$, total do ano)
G7: =BP!$E$2 -> 2025 | I7: Pergunta
E9: IPTU | G9: 0 | I9: Qual o valor das despesas tributárias do período?
E10: IPVA | G10: 0
E11: ICMS DIFAL | G11: 0
E12: Outras despesas tributárias | G12: 0
E14: Total Despesas Tributárias | G14: =SUM(G9:G12) -> 0

Sheet C.08
B2: << Voltar
D5: C.08 | E5: Outras Receitas e Despesas Operacionais
E6: (Valores em R$, total do ano)
G7: =BP!$E$2 -> 2025 | I7: Pergunta
E9: Venda de ativo imobilizado | G9: 0 | I9: Qual o valor das outras receitas operacionais do período?
E10: Prêmios de seguro recebidos | G10: 0
E11: Outras receitas operacionais | G11: 0
E13: Total Outras Receitas Operacionais | G13: =SUM(G9:G11) -> 0
E15: Custo na venda de ativo imobilizado | G15: 0 | I15: Qual o valor das outras despesas operacionais do período?
E16: Perdas deterioração de ativos | G16: 0
E17: Outras despesas operacionais | G17: 0
E19: Total Outras Despesas Operacionais | G19: =SUM(G15:G17) -> 0

Sheet C.09
B2: << Voltar
D5: C.09 | E5: Receitas e Despesas Financeiras
E6: (Valores em R$, total do ano)
G7: =BP!$E$2 -> 2025 | I7: Pergunta
E9: Rendimentos de aplicações financeiras | G9: 0 | I9: Qual o valor das outras receitas financeiras do período?
E10: Juros e multa de mora recebidos | G10: 0
E11: Descontos obtidos | G11: 0
E12: Outras receitas financeiras | G12: 0
E14: Total Receitas Financeiras | G14: =SUM(G9:G12) -> 0
E16: Juros sobre empréstimos e financiamentos | G16: 0 | I16: Qual o valor das outras despesas financeiras do período?
E17: Juros e multa de mora pago | G17: 0
E18: Descontos concedidos | G18: 0
E19: Despesas bancárias | G19: 0
E20: Outras despesas financeiras | G20: 0
E22: Total Despesas Financeiras | G22: =SUM(G16:G20) -> 0

Sheet C.10
B2: << Voltar
D5: C.10 | E5: Provisão de IRPJ e CSLL
E6: (Valores em R$, total do ano)
G7: =BP!$E$2 -> 2025 | I7: Pergunta
I9: Qual o valor das provisões de IRPJ e CSLL do período?
E10: Provisão de IRPJ | G10: 0
E11: Provisão de CSLL | G11: 0
E13: Total Provisão de IRPJ e CSLL | G13: =SUM(G10:G11) -> 0
